GRANNY/GRANNY.py
GRANNY/GRANNY_config.py
GRANNY/GRANNY_copy.py
GRANNY/__init__.py
GRANNY/command.py
GRANNY/test_perf.py
GRANNY/Mask_RCNN/__init__.py
GRANNY/Mask_RCNN/coco.py
GRANNY/Mask_RCNN/config.py
GRANNY/Mask_RCNN/model.py
GRANNY/Mask_RCNN/parallel_model.py
GRANNY/Mask_RCNN/shapes.py
GRANNY/Mask_RCNN/utils.py
GRANNY/Mask_RCNN/visualize.py
granny-1.4.0.dist-info/input_data/4m_TC-1(3)-2-A.JPG
granny-1.4.0.dist-info/input_data/6moPos_TC-1(3)-2-A.JPG
granny-1.4.0.dist-info/input_data/test2_1/4m_TC-1(3)-2-A.JPG
granny-1.4.0.dist-info/LICENSE.txt
granny-1.4.0.dist-info/METADATA
granny-1.4.0.dist-info/WHEEL
granny-1.4.0.dist-info/entry_points.txt
granny-1.4.0.dist-info/top_level.txt
granny-1.4.0.dist-info/RECORD
