Metadata-Version: 2.1
Name: granny
Version: 1.4.0
Summary: GRANNY is an implementation of Mask-RCNN and image processing techniques,        developed by the Ficklin Research Program, to rate disorder severity in "Granny Smith" apple.
Home-page: https://github.com/SystemsGenetics/granny
Author: Nhan H. Nguyen
License: GNU General Public License v3.0
Requires-Python: <3.8
License-File: LICENSE.txt
Requires-Dist: pandas
Requires-Dist: ipython
Requires-Dist: ipykernel
Requires-Dist: numpy
Requires-Dist: opencv-python
Requires-Dist: matplotlib (>=3.5)
Requires-Dist: h5py (<3.0.0)
Requires-Dist: scikit-image (==0.16.2)
Requires-Dist: tensorflow (<=1.15)
Requires-Dist: pillow
Requires-Dist: protobuf (<=3.20)
Requires-Dist: keras (==2.3)
